ruffup/__init__.py
ruffup-0.2.0.dist-info/METADATA
ruffup-0.2.0.dist-info/WHEEL
ruffup-0.2.0.dist-info/entry_points.txt
ruffup-0.2.0.dist-info/RECORD
