Metadata-Version: 2.4
Name: ruffup
Version: 0.2.0
Summary: A very simple tool for running ruff+ruff isort
Author-email: Wayne Werner <wayne@waynewerner.com>
Requires-Python: >=3.12
Requires-Dist: ruff>=0.14.0
